genmq.py
genmq-0.6.2.dist-info/LICENSE
genmq-0.6.2.dist-info/METADATA
genmq-0.6.2.dist-info/WHEEL
genmq-0.6.2.dist-info/entry_points.txt
genmq-0.6.2.dist-info/top_level.txt
genmq-0.6.2.dist-info/RECORD
