Metadata-Version: 2.1
Name: genmq
Version: 0.6.2
Summary: Moodle quiz generator
Author-email: Colin Caprani <colin.caprani@monash.edu>
License: GNU General Public License v3.0
Project-URL: Homepage, https://ccaprani.github.io/genmq/
Project-URL: Documentation, https://ccaprani.github.io/genmq/
Project-URL: Source, https://github.com/ccaprani/genmq/
Project-URL: Tracker, https://github.com/ccaprani/genmq/issues/
Keywords: moodle,quiz,question bank
Platform: any
Classifier: Development Status :: 4 - Beta
Classifier: Topic :: Education :: Computer Aided Instruction (CAI)
Classifier: Environment :: Console
Classifier: Intended Audience :: Education
Classifier: Programming Language :: Python :: 3 :: Only
Classifier: License :: OSI Approved :: GNU General Public License v3 (GPLv3)
Classifier: Natural Language :: English
Classifier: Operating System :: POSIX :: Linux
Classifier: Operating System :: MacOS :: MacOS X
Classifier: Operating System :: Microsoft :: Windows
Classifier: Programming Language :: Python :: 3.8
Classifier: Programming Language :: Python :: 3.9
Requires-Python: >=3.8
License-File: LICENSE
